COPYING
MANIFEST.in
README.md
requirements.txt
setup.py
tox.ini
conf/client.conf.example
conf/client_secrets.json
conf/fedora-messaging-example.toml
conf/settings.py.example
docs/Makefile
docs/admin-guide.rst
docs/api.rst
docs/client-conf.rst
docs/conf.py
docs/developer-guide.rst
docs/greenwave-intersphinx.inv
docs/index.rst
docs/python-intersphinx.inv
docs/release-notes.rst
docs/user-guide.rst
docs/waiverdb-cli.rst
docs/waiverdb.rst
docs/_build/html/objects.inv
tests/__init__.py
tests/client_secrets.json
tests/conftest.py
tests/test_access_control.py
tests/test_api_v10.py
tests/test_app.py
tests/test_auth.py
tests/test_authorization.py
tests/test_cli.py
tests/test_events.py
tests/test_models.py
tests/test_monitor.py
tests/utils.py
waiverdb/__init__.py
waiverdb/api_v1.py
waiverdb/app.py
waiverdb/auth.py
waiverdb/authorization.py
waiverdb/cli.py
waiverdb/config.py
waiverdb/events.py
waiverdb/fields.py
waiverdb/logger.py
waiverdb/manage.py
waiverdb/monitor.py
waiverdb/utils.py
waiverdb/wsgi.py
waiverdb.egg-info/PKG-INFO
waiverdb.egg-info/SOURCES.txt
waiverdb.egg-info/dependency_links.txt
waiverdb.egg-info/entry_points.txt
waiverdb.egg-info/top_level.txt
waiverdb/migrations/README
waiverdb/migrations/__init__.py
waiverdb/migrations/alembic.ini
waiverdb/migrations/env.py
waiverdb/migrations/script.py.mako
waiverdb/migrations/versions/0a27a8ad723a_initial_migration.py
waiverdb/migrations/versions/0a74cdab732a_add_proxyuser_waiving_support.py
waiverdb/migrations/versions/1797bff52162_change_subject_to_jsonb.py
waiverdb/migrations/versions/3868a8118458_add_scenario_field_to_the_database.py
waiverdb/migrations/versions/71b84ccc31bb_migrate_records_from_old_format_to_new.py
waiverdb/migrations/versions/__init__.py
waiverdb/migrations/versions/ce8a1351ecdc_change_subject_to_json.py
waiverdb/migrations/versions/ed43eb9b221c_set_nullable_on_new_and_old_fields.py
waiverdb/migrations/versions/f2772c2c64a6_waive_absence_of_result.py
waiverdb/migrations/versions/f6bc296ba966_subject_dict_to_type_identifier.py
waiverdb/models/__init__.py
waiverdb/models/base.py
waiverdb/models/waivers.py