Metadata-Version: 2.1
Name: waiverdb
Version: 1.4.0
Summary: An engine for storing waivers against test results.
Home-page: UNKNOWN
Author: Red Hat, Inc.
Author-email: qa-devel@lists.fedoraproject.org
License: GPLv2+
Platform: UNKNOWN
License-File: COPYING
